lazilypy/__init__.py
lazilypy/defaults.py
lazilypy/lazy.py
lazilypy/logs.py
lazilypy-0.0.0.dist-info/LICENSE
lazilypy-0.0.0.dist-info/METADATA
lazilypy-0.0.0.dist-info/WHEEL
lazilypy-0.0.0.dist-info/top_level.txt
lazilypy-0.0.0.dist-info/RECORD
